Prompt.py
prompt_wei-0.0.2.dist-info/METADATA
prompt_wei-0.0.2.dist-info/WHEEL
prompt_wei-0.0.2.dist-info/top_level.txt
prompt_wei-0.0.2.dist-info/RECORD
