Metadata-Version: 2.1
Name: prompt-wei
Version: 0.0.2
Summary: UNKNOWN
Home-page: UNKNOWN
License: UNKNOWN
Platform: UNKNOWN
Requires-Dist: pynput (>=1.7.6)
Requires-Dist: six (>=1.16.0)
